llm_install_pack/__init__.py
llm_install_pack-0.1.0.dist-info/LICENSE
llm_install_pack-0.1.0.dist-info/METADATA
llm_install_pack-0.1.0.dist-info/WHEEL
llm_install_pack-0.1.0.dist-info/top_level.txt
llm_install_pack-0.1.0.dist-info/RECORD
