Metadata-Version: 2.1
Name: llm_install_pack
Version: 0.1.0
Summary: A Python Library to download all the required LLM Python packages for building an LLM-based chatbot
Author-email: Sivateja <sivatejaat@gmail.com>
License: MIT License
Requires-Python: >=3.8
License-File: LICENSE
Requires-Dist: transformers
Requires-Dist: accelerate
Requires-Dist: optimum
Requires-Dist: torch
Requires-Dist: tensorflow
Requires-Dist: langchain
Requires-Dist: llama_index
Requires-Dist: openai
Requires-Dist: sentence-transformers
Requires-Dist: pinecone-client
Requires-Dist: weaviate-client
Requires-Dist: chroma
Requires-Dist: qdrant-client
Requires-Dist: tiktoken
Requires-Dist: rich
Requires-Dist: uvicorn
Requires-Dist: fastapi
